[
    {
        "Topic": "Practice Makes Perfect",
        "Problem Statement": "In the following exercises, find the slope of each line shown.",
        "Question": "",
        "Image Links": [
            "https://openstax.org/apps/archive/20240812.170248/resources/2253456cb3117a0820af6c0a3dbb9bff80a4bf38"
        ],
        "Answer": "$$\\frac{2}{5}$$",
        "Answer Image Links": []
    },
    {
        "Topic": "Practice Makes Perfect",
        "Problem Statement": "In the following exercises, find the slope of each line shown.",
        "Question": "",
        "Image Links": [
            "https://openstax.org/apps/archive/20240812.170248/resources/f14a1a85e3633cebac4f5a571179e23b88bf1e8f"
        ],
        "Answer": "",
        "Answer Image Links": []
    },
    {
        "Topic": "Practice Makes Perfect",
        "Problem Statement": "In the following exercises, find the slope of each line shown.",
        "Question": "",
        "Image Links": [
            "https://openstax.org/apps/archive/20240812.170248/resources/7a1e93f2a07534022b95bbf7780d12f978473a26"
        ],
        "Answer": "$$\\frac{5}{4}$$",
        "Answer Image Links": []
    },
    {
        "Topic": "Practice Makes Perfect",
        "Problem Statement": "In the following exercises, find the slope of each line shown.",
        "Question": "",
        "Image Links": [
            "https://openstax.org/apps/archive/20240812.170248/resources/d17d908fe193fcd7fdb1e0872ae05773588f142f"
        ],
        "Answer": "",
        "Answer Image Links": []
    },
    {
        "Topic": "Practice Makes Perfect",
        "Problem Statement": "In the following exercises, find the slope of each line shown.",
        "Question": "",
        "Image Links": [
            "https://openstax.org/apps/archive/20240812.170248/resources/fff70f8e7e94cf3dfa4eb66a0cc94a2abbdc9f78"
        ],
        "Answer": "$$- \\frac{1}{3}$$",
        "Answer Image Links": []
    },
    {
        "Topic": "Practice Makes Perfect",
        "Problem Statement": "In the following exercises, find the slope of each line shown.",
        "Question": "",
        "Image Links": [
            "https://openstax.org/apps/archive/20240812.170248/resources/206ed59760c6f15199e0f2d898e4bf50a8e856e5"
        ],
        "Answer": "",
        "Answer Image Links": []
    },
    {
        "Topic": "Practice Makes Perfect",
        "Problem Statement": "In the following exercises, find the slope of each line shown.",
        "Question": "",
        "Image Links": [
            "https://openstax.org/apps/archive/20240812.170248/resources/2ecef661addc1e7210f770c0afa69db0f3ee1e6b"
        ],
        "Answer": "$$- \\frac{5}{2}$$",
        "Answer Image Links": []
    },
    {
        "Topic": "Practice Makes Perfect",
        "Problem Statement": "In the following exercises, find the slope of each line shown.",
        "Question": "",
        "Image Links": [
            "https://openstax.org/apps/archive/20240812.170248/resources/143a512ee1150e9a339dd7696b6756ca26ddf943"
        ],
        "Answer": "",
        "Answer Image Links": []
    },
    {
        "Topic": "Practice Makes Perfect",
        "Problem Statement": "In the following exercises, find the slope of each line.",
        "Question": "$$y = 3$$",
        "Image Links": [],
        "Answer": "0",
        "Answer Image Links": []
    },
    {
        "Topic": "Practice Makes Perfect",
        "Problem Statement": "In the following exercises, find the slope of each line.",
        "Question": "$$y = -2$$",
        "Image Links": [],
        "Answer": "",
        "Answer Image Links": []
    },
    {
        "Topic": "Practice Makes Perfect",
        "Problem Statement": "In the following exercises, find the slope of each line.",
        "Question": "$$x = -5$$",
        "Image Links": [],
        "Answer": "undefined",
        "Answer Image Links": []
    },
    {
        "Topic": "Practice Makes Perfect",
        "Problem Statement": "In the following exercises, find the slope of each line.",
        "Question": "$$x = 4$$",
        "Image Links": [],
        "Answer": "",
        "Answer Image Links": []
    },
    {
        "Topic": "Practice Makes Perfect",
        "Problem Statement": "In the following exercises, use the slope formula to find the slope of the line between each pair of points.",
        "Question": "$$( 2 , 5 ) , ( 4 , 0 )$$",
        "Image Links": [],
        "Answer": "$$- \\frac{5}{2}$$",
        "Answer Image Links": []
    },
    {
        "Topic": "Practice Makes Perfect",
        "Problem Statement": "In the following exercises, use the slope formula to find the slope of the line between each pair of points.",
        "Question": "$$( 3 , 6 ) , ( 8 , 0 )$$",
        "Image Links": [],
        "Answer": "",
        "Answer Image Links": []
    },
    {
        "Topic": "Practice Makes Perfect",
        "Problem Statement": "In the following exercises, use the slope formula to find the slope of the line between each pair of points.",
        "Question": "$$( -3 , 3 ) , ( 4 , -5 )$$",
        "Image Links": [],
        "Answer": "$$- \\frac{8}{7}$$",
        "Answer Image Links": []
    },
    {
        "Topic": "Practice Makes Perfect",
        "Problem Statement": "In the following exercises, use the slope formula to find the slope of the line between each pair of points.",
        "Question": "$$( -2 , 4 ) , ( 3 , -1 )$$",
        "Image Links": [],
        "Answer": "",
        "Answer Image Links": []
    },
    {
        "Topic": "Practice Makes Perfect",
        "Problem Statement": "In the following exercises, use the slope formula to find the slope of the line between each pair of points.",
        "Question": "$$( -1 , -2 ) , ( 2 , 5 )$$",
        "Image Links": [],
        "Answer": "$$\\frac{7}{3}$$",
        "Answer Image Links": []
    },
    {
        "Topic": "Practice Makes Perfect",
        "Problem Statement": "In the following exercises, use the slope formula to find the slope of the line between each pair of points.",
        "Question": "$$( -2 , -1 ) , ( 6 , 5 )$$",
        "Image Links": [],
        "Answer": "",
        "Answer Image Links": []
    },
    {
        "Topic": "Practice Makes Perfect",
        "Problem Statement": "In the following exercises, use the slope formula to find the slope of the line between each pair of points.",
        "Question": "$$( 4 , -5 ) , ( 1 , -2 )$$",
        "Image Links": [],
        "Answer": "$$-1$$",
        "Answer Image Links": []
    },
    {
        "Topic": "Practice Makes Perfect",
        "Problem Statement": "In the following exercises, use the slope formula to find the slope of the line between each pair of points.",
        "Question": "$$( 3 , -6 ) , ( 2 , -2 )$$",
        "Image Links": [],
        "Answer": "",
        "Answer Image Links": []
    },
    {
        "Topic": "Practice Makes Perfect",
        "Problem Statement": "In the following exercises, graph each line with the given point and slope.",
        "Question": "$$( 2 , 5 ) ;$$ $$m = - \\frac{1}{3}$$",
        "Image Links": [],
        "Answer": "",
        "Answer Image Links": [
            "https://openstax.org/apps/archive/20240812.170248/resources/d379158a2319542b675fd0e177e226b85ffb8e33"
        ]
    },
    {
        "Topic": "Practice Makes Perfect",
        "Problem Statement": "In the following exercises, graph each line with the given point and slope.",
        "Question": "$$( 1 , 4 )$$ ; $$m = - \\frac{1}{2}$$",
        "Image Links": [],
        "Answer": "",
        "Answer Image Links": []
    },
    {
        "Topic": "Practice Makes Perfect",
        "Problem Statement": "In the following exercises, graph each line with the given point and slope.",
        "Question": "$$( -1 , -4 )$$ ; $$m = \\frac{4}{3}$$",
        "Image Links": [],
        "Answer": "",
        "Answer Image Links": [
            "https://openstax.org/apps/archive/20240812.170248/resources/2e15e26aafeca59b6c217cc7c6a93ed3736209d1"
        ]
    },
    {
        "Topic": "Practice Makes Perfect",
        "Problem Statement": "In the following exercises, graph each line with the given point and slope.",
        "Question": "$$( -3 , -5 )$$ ; $$m = \\frac{3}{2}$$",
        "Image Links": [],
        "Answer": "",
        "Answer Image Links": []
    },
    {
        "Topic": "Practice Makes Perfect",
        "Problem Statement": "In the following exercises, graph each line with the given point and slope.",
        "Question": "y -intercept 3; $$m = - \\frac{2}{5}$$",
        "Image Links": [],
        "Answer": "",
        "Answer Image Links": [
            "https://openstax.org/apps/archive/20240812.170248/resources/f68be3227818578aab3c467c398c03a0e6d8bd92"
        ]
    },
    {
        "Topic": "Practice Makes Perfect",
        "Problem Statement": "In the following exercises, graph each line with the given point and slope.",
        "Question": "x -intercept $$-2$$ ; $$m = \\frac{3}{4}$$",
        "Image Links": [],
        "Answer": "",
        "Answer Image Links": []
    },
    {
        "Topic": "Practice Makes Perfect",
        "Problem Statement": "In the following exercises, graph each line with the given point and slope.",
        "Question": "$$( -4 , 2 )$$ ; $$m = 4$$",
        "Image Links": [],
        "Answer": "",
        "Answer Image Links": [
            "https://openstax.org/apps/archive/20240812.170248/resources/7277f3108d21d5408080cba8ef6f650bb9e9e87c"
        ]
    },
    {
        "Topic": "Practice Makes Perfect",
        "Problem Statement": "In the following exercises, graph each line with the given point and slope.",
        "Question": "$$( 1 , 5 )$$ ; $$m = -3$$",
        "Image Links": [],
        "Answer": "",
        "Answer Image Links": []
    },
    {
        "Topic": "Practice Makes Perfect",
        "Problem Statement": "In the following exercises, identify the slope and y -intercept of each line.",
        "Question": "$$y = -7 x + 3$$",
        "Image Links": [],
        "Answer": "$$m = -7 ; ( 0 , 3 )$$",
        "Answer Image Links": []
    },
    {
        "Topic": "Practice Makes Perfect",
        "Problem Statement": "In the following exercises, identify the slope and y -intercept of each line.",
        "Question": "$$y = 4 x - 10$$",
        "Image Links": [],
        "Answer": "",
        "Answer Image Links": []
    },
    {
        "Topic": "Practice Makes Perfect",
        "Problem Statement": "In the following exercises, identify the slope and y -intercept of each line.",
        "Question": "$$3 x + y = 5$$",
        "Image Links": [],
        "Answer": "$$m = -3 ; ( 0 , 5 )$$",
        "Answer Image Links": []
    },
    {
        "Topic": "Practice Makes Perfect",
        "Problem Statement": "In the following exercises, identify the slope and y -intercept of each line.",
        "Question": "$$4 x + y = 8$$",
        "Image Links": [],
        "Answer": "",
        "Answer Image Links": []
    },
    {
        "Topic": "Practice Makes Perfect",
        "Problem Statement": "In the following exercises, identify the slope and y -intercept of each line.",
        "Question": "$$6 x + 4 y = 12$$",
        "Image Links": [],
        "Answer": "$$m = - \\frac{3}{2} ; ( 0 , 3 )$$",
        "Answer Image Links": []
    },
    {
        "Topic": "Practice Makes Perfect",
        "Problem Statement": "In the following exercises, identify the slope and y -intercept of each line.",
        "Question": "$$8 x + 3 y = 12$$",
        "Image Links": [],
        "Answer": "",
        "Answer Image Links": []
    },
    {
        "Topic": "Practice Makes Perfect",
        "Problem Statement": "In the following exercises, identify the slope and y -intercept of each line.",
        "Question": "$$5 x - 2 y = 6$$",
        "Image Links": [],
        "Answer": "$$m = \\frac{5}{2} ; ( 0 , -3 )$$",
        "Answer Image Links": []
    },
    {
        "Topic": "Practice Makes Perfect",
        "Problem Statement": "In the following exercises, identify the slope and y -intercept of each line.",
        "Question": "$$7 x - 3 y = 9$$",
        "Image Links": [],
        "Answer": "",
        "Answer Image Links": []
    },
    {
        "Topic": "Practice Makes Perfect",
        "Problem Statement": "In the following exercises, graph the line of each equation using its slope and y -intercept.",
        "Question": "$$y = 3 x - 1$$",
        "Image Links": [],
        "Answer": "",
        "Answer Image Links": [
            "https://openstax.org/apps/archive/20240812.170248/resources/579989c6779274e4dc354e8f6e39290291d20db9"
        ]
    },
    {
        "Topic": "Practice Makes Perfect",
        "Problem Statement": "In the following exercises, graph the line of each equation using its slope and y -intercept.",
        "Question": "$$y = 2 x - 3$$",
        "Image Links": [],
        "Answer": "",
        "Answer Image Links": []
    },
    {
        "Topic": "Practice Makes Perfect",
        "Problem Statement": "In the following exercises, graph the line of each equation using its slope and y -intercept.",
        "Question": "$$y = \\text{unicode[:-]} x + 3$$",
        "Image Links": [],
        "Answer": "",
        "Answer Image Links": [
            "https://openstax.org/apps/archive/20240812.170248/resources/7aa0da916e260539e10aaee81a0a7205bb1de295"
        ]
    },
    {
        "Topic": "Practice Makes Perfect",
        "Problem Statement": "In the following exercises, graph the line of each equation using its slope and y -intercept.",
        "Question": "$$y = \\text{unicode[:-]} x - 4$$",
        "Image Links": [],
        "Answer": "",
        "Answer Image Links": []
    },
    {
        "Topic": "Practice Makes Perfect",
        "Problem Statement": "In the following exercises, graph the line of each equation using its slope and y -intercept.",
        "Question": "$$y = - \\frac{2}{5} x - 3$$",
        "Image Links": [],
        "Answer": "",
        "Answer Image Links": [
            "https://openstax.org/apps/archive/20240812.170248/resources/0a07bf6b01c3c83f61ebf23a675be9fc580863b7"
        ]
    },
    {
        "Topic": "Practice Makes Perfect",
        "Problem Statement": "In the following exercises, graph the line of each equation using its slope and y -intercept.",
        "Question": "$$y = - \\frac{3}{5} x + 2$$",
        "Image Links": [],
        "Answer": "",
        "Answer Image Links": []
    },
    {
        "Topic": "Practice Makes Perfect",
        "Problem Statement": "In the following exercises, graph the line of each equation using its slope and y -intercept.",
        "Question": "$$3 x - 2 y = 4$$",
        "Image Links": [],
        "Answer": "",
        "Answer Image Links": [
            "https://openstax.org/apps/archive/20240812.170248/resources/156b2459a540ea54e4ca1285e290d753ae057d30"
        ]
    },
    {
        "Topic": "Practice Makes Perfect",
        "Problem Statement": "In the following exercises, graph the line of each equation using its slope and y -intercept.",
        "Question": "$$3 x - 4 y = 8$$",
        "Image Links": [],
        "Answer": "",
        "Answer Image Links": []
    },
    {
        "Topic": "Practice Makes Perfect",
        "Problem Statement": "In the following exercises, determine the most convenient method to graph each line.",
        "Question": "$$x = 2$$",
        "Image Links": [],
        "Answer": "vertical line",
        "Answer Image Links": []
    },
    {
        "Topic": "Practice Makes Perfect",
        "Problem Statement": "In the following exercises, determine the most convenient method to graph each line.",
        "Question": "$$y = 5$$",
        "Image Links": [],
        "Answer": "",
        "Answer Image Links": []
    },
    {
        "Topic": "Practice Makes Perfect",
        "Problem Statement": "In the following exercises, determine the most convenient method to graph each line.",
        "Question": "$$y = -3 x + 4$$",
        "Image Links": [],
        "Answer": "slope-intercept",
        "Answer Image Links": []
    },
    {
        "Topic": "Practice Makes Perfect",
        "Problem Statement": "In the following exercises, determine the most convenient method to graph each line.",
        "Question": "$$x - y = 5$$",
        "Image Links": [],
        "Answer": "",
        "Answer Image Links": []
    },
    {
        "Topic": "Practice Makes Perfect",
        "Problem Statement": "In the following exercises, determine the most convenient method to graph each line.",
        "Question": "$$x - y = 1$$",
        "Image Links": [],
        "Answer": "intercepts",
        "Answer Image Links": []
    },
    {
        "Topic": "Practice Makes Perfect",
        "Problem Statement": "In the following exercises, determine the most convenient method to graph each line.",
        "Question": "$$y = \\frac{2}{3} x - 1$$",
        "Image Links": [],
        "Answer": "",
        "Answer Image Links": []
    },
    {
        "Topic": "Practice Makes Perfect",
        "Problem Statement": "In the following exercises, determine the most convenient method to graph each line.",
        "Question": "$$3 x - 2 y = -12$$",
        "Image Links": [],
        "Answer": "intercepts",
        "Answer Image Links": []
    },
    {
        "Topic": "Practice Makes Perfect",
        "Problem Statement": "In the following exercises, determine the most convenient method to graph each line.",
        "Question": "$$2 x - 5 y = -10$$",
        "Image Links": [],
        "Answer": "",
        "Answer Image Links": []
    },
    {
        "Topic": "Practice Makes Perfect",
        "Problem Statement": "Graph and Interpret Applications of Slope-Intercept",
        "Question": "The equation $$P = 31 + 1.75 w$$ models the relation between the amount of Tuyet\u2019s monthly water bill payment, P , in dollars, and the number of units of water, w , used. \u24d0 Find Tuyet\u2019s payment for a month when 0 units of water are used. \u24d1 Find Tuyet\u2019s payment for a month when 12 units of water are used. \u24d2 Interpret the slope and P -intercept of the equation. \u24d3 Graph the equation.",
        "Image Links": [],
        "Answer": "\u24d0 $31 \u24d1 $52 \u24d2 The slope, $$1.75 ,$$ means that the payment, P , increases by $$\\text{$} 1.75$$ when the number of units of water used, w, increases by 1. The P -intercept means that when the number units of water Tuyet used is 0, the payment is $31. \u24d3",
        "Answer Image Links": [
            "https://openstax.org/apps/archive/20240812.170248/resources/491e4318cf9c1c34a498959d978652d2270acb16"
        ]
    },
    {
        "Topic": "Practice Makes Perfect",
        "Problem Statement": "Graph and Interpret Applications of Slope-Intercept",
        "Question": "The equation $$P = 28 + 2.54 w$$ models the relation between the amount of R and y\u2019s monthly water bill payment, P , in dollars, and the number of units of water, w , used. \u24d0 Find the payment for a month when R and y used 0 units of water. \u24d1 Find the payment for a month when R and y used 15 units of water. \u24d2 Interpret the slope and P -intercept of the equation. \u24d3 Graph the equation.",
        "Image Links": [],
        "Answer": "",
        "Answer Image Links": []
    },
    {
        "Topic": "Practice Makes Perfect",
        "Problem Statement": "Graph and Interpret Applications of Slope-Intercept",
        "Question": "Bruce drives his car for his job. The equation $$R = 0.575 m + 42$$ models the relation between the amount in dollars, R , that he is reimbursed and the number of miles, m , he drives in one day. \u24d0 Find the amount Bruce is reimbursed on a day when he drives 0 miles. \u24d1 Find the amount Bruce is reimbursed on a day when he drives 220 miles. \u24d2 Interpret the slope and R -intercept of the equation. \u24d3 Graph the equation.",
        "Image Links": [],
        "Answer": "\u24d0 $42 \u24d1 $168.50 \u24d2 The slope, 0.575 means that the amount he is reimbursed, R , increases by $0.575 when the number of miles driven, m, increases by 1. The R -intercept means that when the number miles driven is 0, the amount reimbursed is $42. \u24d3",
        "Answer Image Links": [
            "https://openstax.org/apps/archive/20240812.170248/resources/66563a53763033528881a56847bb04298182f4cf"
        ]
    },
    {
        "Topic": "Practice Makes Perfect",
        "Problem Statement": "Graph and Interpret Applications of Slope-Intercept",
        "Question": "Janelle is planning to rent a car while on vacation. The equation $$C = 0.32 m + 15$$ models the relation between the cost in dollars, C , per day and the number of miles, m , she drives in one day. \u24d0 Find the cost if Janelle drives the car 0 miles one day. \u24d1 Find the cost on a day when Janelle drives the car 400 miles. \u24d2 Interpret the slope and C -intercept of the equation. \u24d3 Graph the equation.",
        "Image Links": [],
        "Answer": "",
        "Answer Image Links": []
    },
    {
        "Topic": "Practice Makes Perfect",
        "Problem Statement": "Graph and Interpret Applications of Slope-Intercept",
        "Question": "Cherie works in retail and her weekly salary includes commission for the amount she sells. The equation $$S = 400 + 0.15 c$$ models the relation between her weekly salary, S , in dollars and the amount of her sales, c , in dollars. \u24d0 Find Cherie\u2019s salary for a week when her sales were $0. \u24d1 Find Cherie\u2019s salary for a week when her sales were $3,600. \u24d2 Interpret the slope and S -intercept of the equation. \u24d3 Graph the equation.",
        "Image Links": [],
        "Answer": "\u24d0 $400 \u24d1 $940 \u24d2 The slope, $$0.15 ,$$ means that Cherie\u2019s salary, S , increases by $0.15 for every $1 increase in her sales. The S -intercept means that when her sales are $0, her salary is $400. \u24d3",
        "Answer Image Links": [
            "https://openstax.org/apps/archive/20240812.170248/resources/642dcb723395d06ce42d082ef51be742b83310b2"
        ]
    },
    {
        "Topic": "Practice Makes Perfect",
        "Problem Statement": "Graph and Interpret Applications of Slope-Intercept",
        "Question": "Patel\u2019s weekly salary includes a base pay plus commission on his sales. The equation $$S = 750 + 0.09 c$$ models the relation between his weekly salary, S , in dollars and the amount of his sales, c , in dollars. \u24d0 Find Patel\u2019s salary for a week when his sales were 0. \u24d1 Find Patel\u2019s salary for a week when his sales were 18,540. \u24d2 Interpret the slope and S -intercept of the equation. \u24d3 Graph the equation.",
        "Image Links": [],
        "Answer": "",
        "Answer Image Links": []
    },
    {
        "Topic": "Practice Makes Perfect",
        "Problem Statement": "Graph and Interpret Applications of Slope-Intercept",
        "Question": "Costa is planning a lunch banquet. The equation $$C = 450 + 28 g$$ models the relation between the cost in dollars, C , of the banquet and the number of guests, g . \u24d0 Find the cost if the number of guests is 40. \u24d1 Find the cost if the number of guests is 80. \u24d2 Interpret the slope and C -intercept of the equation. \u24d3 Graph the equation.",
        "Image Links": [],
        "Answer": "\u24d0 $1570 \u24d1 $2690 \u24d2 The slope gives the cost per guest. The slope, 28, means that the cost, C , increases by $28 when the number of guests increases by 1. The C -intercept means that if the number of guests was 0, the cost would be $450. \u24d3",
        "Answer Image Links": [
            "https://openstax.org/apps/archive/20240812.170248/resources/07f68a1926c6f8a5f79b3d975bb7e5d50622ecc7"
        ]
    },
    {
        "Topic": "Practice Makes Perfect",
        "Problem Statement": "Graph and Interpret Applications of Slope-Intercept",
        "Question": "Margie is planning a dinner banquet. The equation $$C = 750 + 42 g$$ models the relation between the cost in dollars, C of the banquet and the number of guests, g . \u24d0 Find the cost if the number of guests is 50. \u24d1 Find the cost if the number of guests is 100. \u24d2 Interpret the slope and C -intercept of the equation. \u24d3 Graph the equation.",
        "Image Links": [],
        "Answer": "",
        "Answer Image Links": []
    },
    {
        "Topic": "Practice Makes Perfect",
        "Problem Statement": "In the following exercises, use slopes and y -intercepts to determine if the lines are parallel, perpendicular, or neither.",
        "Question": "$$y = \\frac{3}{4} x - 3 ; 3 x - 4 y = -2$$",
        "Image Links": [],
        "Answer": "parallel",
        "Answer Image Links": []
    },
    {
        "Topic": "Practice Makes Perfect",
        "Problem Statement": "In the following exercises, use slopes and y -intercepts to determine if the lines are parallel, perpendicular, or neither.",
        "Question": "$$3 x + 4 y = - 2 ; y = \\frac{3}{4} x - 3$$",
        "Image Links": [],
        "Answer": "",
        "Answer Image Links": []
    },
    {
        "Topic": "Practice Makes Perfect",
        "Problem Statement": "In the following exercises, use slopes and y -intercepts to determine if the lines are parallel, perpendicular, or neither.",
        "Question": "$$2 x - 4 y = 6 ; x - 2 y = 3$$",
        "Image Links": [],
        "Answer": "neither",
        "Answer Image Links": []
    },
    {
        "Topic": "Practice Makes Perfect",
        "Problem Statement": "In the following exercises, use slopes and y -intercepts to determine if the lines are parallel, perpendicular, or neither.",
        "Question": "$$8 x + 6 y = 6 ; 12 x + 9 y = 12$$",
        "Image Links": [],
        "Answer": "",
        "Answer Image Links": []
    },
    {
        "Topic": "Practice Makes Perfect",
        "Problem Statement": "In the following exercises, use slopes and y -intercepts to determine if the lines are parallel, perpendicular, or neither.",
        "Question": "$$x = 5 ; x = -6$$",
        "Image Links": [],
        "Answer": "parallel",
        "Answer Image Links": []
    },
    {
        "Topic": "Practice Makes Perfect",
        "Problem Statement": "In the following exercises, use slopes and y -intercepts to determine if the lines are parallel, perpendicular, or neither.",
        "Question": "$$x = - 3 ; x = - 2$$",
        "Image Links": [],
        "Answer": "",
        "Answer Image Links": []
    },
    {
        "Topic": "Practice Makes Perfect",
        "Problem Statement": "In the following exercises, use slopes and y -intercepts to determine if the lines are parallel, perpendicular, or neither.",
        "Question": "$$4 x - 2 y = 5 ; 3 x + 6 y = 8$$",
        "Image Links": [],
        "Answer": "perpendicular",
        "Answer Image Links": []
    },
    {
        "Topic": "Practice Makes Perfect",
        "Problem Statement": "In the following exercises, use slopes and y -intercepts to determine if the lines are parallel, perpendicular, or neither.",
        "Question": "$$8 x - 2 y = 7 ; 3 x + 12 y = 9$$",
        "Image Links": [],
        "Answer": "",
        "Answer Image Links": []
    },
    {
        "Topic": "Practice Makes Perfect",
        "Problem Statement": "In the following exercises, use slopes and y -intercepts to determine if the lines are parallel, perpendicular, or neither.",
        "Question": "$$3 x - 6 y = 12 ; 6 x - 3 y = 3$$",
        "Image Links": [],
        "Answer": "neither",
        "Answer Image Links": []
    },
    {
        "Topic": "Practice Makes Perfect",
        "Problem Statement": "In the following exercises, use slopes and y -intercepts to determine if the lines are parallel, perpendicular, or neither.",
        "Question": "$$9 x - 5 y = 4 ; 5 x + 9 y = - 1$$",
        "Image Links": [],
        "Answer": "",
        "Answer Image Links": []
    },
    {
        "Topic": "Practice Makes Perfect",
        "Problem Statement": "In the following exercises, use slopes and y -intercepts to determine if the lines are parallel, perpendicular, or neither.",
        "Question": "$$7 x - 4 y = 8 ; 4 x + 7 y = 14$$",
        "Image Links": [],
        "Answer": "perpendicular",
        "Answer Image Links": []
    },
    {
        "Topic": "Practice Makes Perfect",
        "Problem Statement": "In the following exercises, use slopes and y -intercepts to determine if the lines are parallel, perpendicular, or neither.",
        "Question": "$$5 x - 2 y = 11 ; 5 x - y = 7$$",
        "Image Links": [],
        "Answer": "",
        "Answer Image Links": []
    },
    {
        "Topic": "Practice Makes Perfect",
        "Problem Statement": "In the following exercises, use slopes and y -intercepts to determine if the lines are parallel, perpendicular, or neither.",
        "Question": "$$3 x - 2 y = 8 ; 2 x + 3 y = 6$$",
        "Image Links": [],
        "Answer": "perpendicular",
        "Answer Image Links": []
    },
    {
        "Topic": "Practice Makes Perfect",
        "Problem Statement": "In the following exercises, use slopes and y -intercepts to determine if the lines are parallel, perpendicular, or neither.",
        "Question": "$$2 x + 3 y = 5 ; 3 x - 2 y = 7$$",
        "Image Links": [],
        "Answer": "",
        "Answer Image Links": []
    },
    {
        "Topic": "Practice Makes Perfect",
        "Problem Statement": "In the following exercises, use slopes and y -intercepts to determine if the lines are parallel, perpendicular, or neither.",
        "Question": "$$3 x - 2 y = 1 ; 2 x - 3 y = 2$$",
        "Image Links": [],
        "Answer": "neither",
        "Answer Image Links": []
    },
    {
        "Topic": "Practice Makes Perfect",
        "Problem Statement": "In the following exercises, use slopes and y -intercepts to determine if the lines are parallel, perpendicular, or neither.",
        "Question": "$$2 x + 4 y = 3 ; 6 x + 3 y = 2$$",
        "Image Links": [],
        "Answer": "",
        "Answer Image Links": []
    },
    {
        "Topic": "Practice Makes Perfect",
        "Problem Statement": "In the following exercises, use slopes and y -intercepts to determine if the lines are parallel, perpendicular, or neither.",
        "Question": "$$y = 2 ; y = 6$$",
        "Image Links": [],
        "Answer": "parallel",
        "Answer Image Links": []
    },
    {
        "Topic": "Practice Makes Perfect",
        "Problem Statement": "In the following exercises, use slopes and y -intercepts to determine if the lines are parallel, perpendicular, or neither.",
        "Question": "$$y = - 1 ; y = 2$$",
        "Image Links": [],
        "Answer": "",
        "Answer Image Links": []
    },
    {
        "Topic": "Writing Exercises",
        "Problem Statement": "",
        "Question": "How does the graph of a line with slope $$m = - \\frac{1}{2}$$ differ from the graph of a line with slope $$m = 2 ?$$",
        "Image Links": [],
        "Answer": "It is perpendicular to the second line.",
        "Answer Image Links": []
    },
    {
        "Topic": "Writing Exercises",
        "Problem Statement": "",
        "Question": "Why is the slope of a vertical line \u201cundefined\u201d?",
        "Image Links": [],
        "Answer": "",
        "Answer Image Links": []
    },
    {
        "Topic": "Writing Exercises",
        "Problem Statement": "",
        "Question": "Explain how you can graph a line given a point and its slope.",
        "Image Links": [],
        "Answer": "Answers will vary.",
        "Answer Image Links": []
    },
    {
        "Topic": "Writing Exercises",
        "Problem Statement": "",
        "Question": "Explain in your own words how to decide which method to use to graph a line.",
        "Image Links": [],
        "Answer": "",
        "Answer Image Links": []
    }
]