[
    {
        "Topic": "9.1 Electrical Current",
        "Problem Statement": "",
        "Question": "A Van de Graaff generator is one of the original particle accelerators and can be used to accelerate charged particles like protons or electrons. You may have seen it used to make human hair stand on end or produce large sparks. One application of the Van de Graaff generator is to create X-rays by bombarding a hard metal target with the beam. Consider a beam of protons at 1.00 keV and a current of 5.00 mA produced by the generator. (a) What is the speed of the protons? (b) How many protons are produced each second?",
        "Image Links": [],
        "Answer": "a. $$v = 4.38 \\times 10^{5} \\frac{\\text{m}}{\\text{s}}$$ ; b. $$\\text{Delta} q = 5.00 \\times 10^{-3} \\text{C} , \\text{no. of protons} = 3.13 \\times 10^{16}$$",
        "Answer Image Links": []
    },
    {
        "Topic": "9.1 Electrical Current",
        "Problem Statement": "",
        "Question": "A cathode ray tube (CRT) is a device that produces a focused beam of electrons in a vacuum. The electrons strike a phosphor-coated glass screen at the end of the tube, which produces a bright spot of light. The position of the bright spot of light on the screen can be adjusted by deflecting the electrons with electrical fields, magnetic fields, or both. Although the CRT tube was once commonly found in televisions, computer displays, and oscilloscopes, newer appliances use a liquid crystal display (LCD) or plasma screen. You still may come across a CRT in your study of science. Consider a CRT with an electron beam average current of $$25.00 \\mu \\text{A}$$ . How many electrons strike the screen every minute?",
        "Image Links": [],
        "Answer": "",
        "Answer Image Links": []
    },
    {
        "Topic": "9.1 Electrical Current",
        "Problem Statement": "",
        "Question": "How many electrons flow through a point in a wire in 3.00 s if there is a constant current of $$I = 4.00 \\text{A}$$ ?",
        "Image Links": [],
        "Answer": "$$I = \\frac{\\text{Delta} Q}{\\text{Delta} t} , \\text{Delta} Q = 12.00 \\text{C}$$ no. of electrons = $$7.5 \\times 10^{19}$$",
        "Answer Image Links": []
    },
    {
        "Topic": "9.1 Electrical Current",
        "Problem Statement": "",
        "Question": "A conductor carries a current that is decreasing exponentially with time. The current is modeled as $$I = I_{0} e^{\\text{unicode[:-]} t \\text{/} \\tau}$$ , where $$I_{0} = 3.00 \\text{A}$$ is the current at time $$t = 0.00 \\text{s}$$ and $$\\tau = 0.50 \\text{s}$$ is the time constant. How much charge flows through the conductor between $$t = 0.00 \\text{s}$$ and $$t = 3 \\tau$$ ?",
        "Image Links": [],
        "Answer": "",
        "Answer Image Links": []
    },
    {
        "Topic": "9.1 Electrical Current",
        "Problem Statement": "",
        "Question": "The quantity of charge through a conductor is modeled as $$Q = 4.00 \\frac{\\text{C}}{\\text{s}^{4}} t^{4} - 1.00 \\frac{\\text{C}}{\\text{s}} t + 6.00 \\text{mC}$$ . What is the current at time $$t = 3.00 \\text{s}$$ ?",
        "Image Links": [],
        "Answer": "$$\\left .\\begin{matrix}{} \\\\  \\\\ I ( t ) = 0.016 \\frac{\\text{C}}{\\text{s}^{4}} t^{3} - 0.001 \\frac{\\text{C}}{\\text{s}} \\\\ I ( 3.00 \\text{s} ) = 0.431 \\text{A}\\end{matrix}\\right .$$",
        "Answer Image Links": []
    },
    {
        "Topic": "9.1 Electrical Current",
        "Problem Statement": "",
        "Question": "The current through a conductor is modeled as $$I ( t ) = I_{m} \\text{sin} ( 2 \\pi [ 60 \\text{Hz} ] t )$$ . Write an equation for the charge as a function of time.",
        "Image Links": [],
        "Answer": "",
        "Answer Image Links": []
    },
    {
        "Topic": "9.1 Electrical Current",
        "Problem Statement": "",
        "Question": "The charge on a capacitor in a circuit is modeled as $$Q ( t ) = Q_{\\text{max}} \\text{cos} ( \\upomega t + \\upphi )$$ . What is the current through the circuit as a function of time?",
        "Image Links": [],
        "Answer": "$$I ( t ) = \\text{unicode[:-]} I_{\\text{max}} \\text{sin} ( \\upomega t + \\upphi )$$",
        "Answer Image Links": []
    },
    {
        "Topic": "9.2 Model of Conduction in Metals",
        "Problem Statement": "",
        "Question": "An aluminum wire 1.628 mm in diameter (14-gauge) carries a current of 3.00 amps. (a) What is the absolute value of the charge density in the wire? (b) What is the drift velocity of the electrons? (c) What would be the drift velocity if the same gauge copper were used instead of aluminum? The density of copper is $$8.96 \\text{g/cm}^{3}$$ and the density of aluminum is $$2.70 \\text{g/cm}^{3}$$ . The molar mass of aluminum is 26.98 g/mol and the molar mass of copper is 63.5 g/mol. Assume each atom of metal contributes one free electron.",
        "Image Links": [],
        "Answer": "",
        "Answer Image Links": []
    },
    {
        "Topic": "9.2 Model of Conduction in Metals",
        "Problem Statement": "",
        "Question": "The current of an electron beam has a measured current of $$I = 50.00 \\mu \\text{A}$$ with a radius of 1.00 mm. What is the magnitude of the current density of the beam?",
        "Image Links": [],
        "Answer": "$$| J | = 15.92 \\text{A/m}^{2}$$",
        "Answer Image Links": []
    },
    {
        "Topic": "9.2 Model of Conduction in Metals",
        "Problem Statement": "",
        "Question": "A high-energy proton accelerator produces a proton beam with a radius of $$r = 0.90 \\text{mm}$$ . The beam current is $$I = 9.00 \\mu \\text{A}$$ and is constant. The charge density of the beam is $$n = 6.00 \\times 10^{11}$$ protons per cubic meter. (a) What is the current density of the beam? (b) What is the drift velocity of the beam? (c) How much time does it take for $$1.00 \\times 10^{10}$$ protons to be emitted by the accelerator?",
        "Image Links": [],
        "Answer": "",
        "Answer Image Links": []
    },
    {
        "Topic": "9.2 Model of Conduction in Metals",
        "Problem Statement": "",
        "Question": "Consider a wire of a circular cross-section with a radius of $$R = 3.00 \\text{mm}$$ . The magnitude of the current density is modeled as $$J = c r^{2} = 5.00 \\times 10^{6} \\frac{\\text{A}}{\\text{m}^{4}} r^{2}$$ . What is the current through the inner section of the wire from the center to $$r = 0.5 R$$ ?",
        "Image Links": [],
        "Answer": "$$I = 3.98 \\times 10^{-5} \\text{A}$$",
        "Answer Image Links": []
    },
    {
        "Topic": "9.2 Model of Conduction in Metals",
        "Problem Statement": "",
        "Question": "A cylindrical wire has a current density from the center of the wire\u2019s cross section as $$J ( r ) = C r^{2}$$ where $$r$$ is in meters, $$J$$ is in amps per square meter, and $$C = 10^{3} \\text{A/m}^{4}$$ . This current density continues to the end of the wire at a radius of 1.0 mm. Calculate the current just outside of this wire.",
        "Image Links": [],
        "Answer": "",
        "Answer Image Links": []
    },
    {
        "Topic": "9.2 Model of Conduction in Metals",
        "Problem Statement": "",
        "Question": "The current supplied to an air conditioner unit is 4.00 amps. The air conditioner is wired using a 10-gauge (diameter 2.588 mm) wire. The charge density is $$n = 8.48 \\times 10^{28} \\frac{\\text{electrons}}{\\text{m}^{3}}$$ . Find the magnitude of (a) current density and (b) the drift velocity.",
        "Image Links": [],
        "Answer": "a. $$| J | = 7.60 \\times 10^{5} \\frac{\\text{A}}{\\text{m}^{2}}$$ ; b. $$v_{\\text{d}} = 5.60 \\times 10^{-5} \\frac{\\text{m}}{\\text{s}}$$",
        "Answer Image Links": []
    },
    {
        "Topic": "9.4 Ohm's Law",
        "Problem Statement": "",
        "Question": "A $$2.2 \\text{-k} \\text{omega}$$ resistor is connected across a D cell battery (1.5 V). What is the current through the resistor?",
        "Image Links": [],
        "Answer": "",
        "Answer Image Links": []
    },
    {
        "Topic": "9.4 Ohm's Law",
        "Problem Statement": "",
        "Question": "A resistor rated at $$250 \\text{k} \\text{omega}$$ is connected across two D cell batteries (each 1.50 V) in series, with a total voltage of 3.00 V. The manufacturer advertises that their resistors are within 5% of the rated value. What are the possible minimum current and maximum current through the resistor?",
        "Image Links": [],
        "Answer": "$$\\left .\\begin{matrix}{} \\\\  \\\\ R_{\\text{min}} = 2.375 \\times 10^{5} \\text{omega} , I_{\\text{min}} = 12.63 \\mu \\text{A} \\\\ R_{\\text{max}} = 2.625 \\times 10^{5} \\text{omega} , I_{\\text{max}} = 11.43 \\mu \\text{A}\\end{matrix}\\right .$$",
        "Answer Image Links": []
    },
    {
        "Topic": "9.4 Ohm's Law",
        "Problem Statement": "",
        "Question": "A resistor is connected in series with a power supply of 20.00 V. The current measure is 0.50 A. What is the resistance of the resistor?",
        "Image Links": [],
        "Answer": "",
        "Answer Image Links": []
    },
    {
        "Topic": "9.4 Ohm's Law",
        "Problem Statement": "",
        "Question": "A resistor is placed in a circuit with an adjustable voltage source. The voltage across and the current through the resistor and the measurements are shown below. Estimate the resistance of the resistor.",
        "Image Links": [
            "https://openstax.org/apps/archive/20240812.170248/resources/943dec101624b83fa4c10bc6be7ef8120880a2e3"
        ],
        "Answer": "$$R = 100 \\text{omega}$$",
        "Answer Image Links": []
    },
    {
        "Topic": "9.4 Ohm's Law",
        "Problem Statement": "",
        "Question": "The following table show the measurements of a current through and the voltage across a sample of material. Plot the data, and assuming the object is an ohmic device, estimate the resistance. \\begin{table}[h]\n\\centering\n\\begin{tabular}{|c|c|}\n\\hline\nI(A) & V(V) \\\\ \\hline\n0 & 3 \\\\ \\hline\n2 & 23 \\\\ \\hline\n4 & 39 \\\\ \\hline\n6 & 58 \\\\ \\hline\n8 & 77 \\\\ \\hline\n10 & 100 \\\\ \\hline\n12 & 119 \\\\ \\hline\n14 & 142 \\\\ \\hline\n16 & 162 \\\\ \\hline\n\\end{tabular}\n\\end{table}",
        "Image Links": [],
        "Answer": "",
        "Answer Image Links": []
    },
    {
        "Topic": "9.5 Electrical Energy and Power",
        "Problem Statement": "",
        "Question": "A $$20.00 \\text{-V}$$ battery is used to supply current to a $$10 \\text{-k} \\text{omega}$$ resistor. Assume the voltage drop across any wires used for connections is negligible. (a) What is the current through the resistor? (b) What is the power dissipated by the resistor? (c) What is the power input from the battery, assuming all the electrical power is dissipated by the resistor? (d) What happens to the energy dissipated by the resistor?",
        "Image Links": [],
        "Answer": "a. $$I = 2 \\text{mA}$$ ; b. $$P = 0.04 \\text{W}$$ ; c. $$P = 0.04 \\text{W}$$ ; d. It is converted into heat.",
        "Answer Image Links": []
    },
    {
        "Topic": "9.5 Electrical Energy and Power",
        "Problem Statement": "",
        "Question": "What is the maximum voltage that can be applied to a $$20 \\text{-k} \\text{omega}$$ resistor rated at $$\\frac{1}{4} \\text{W}$$ ?",
        "Image Links": [],
        "Answer": "",
        "Answer Image Links": []
    },
    {
        "Topic": "9.5 Electrical Energy and Power",
        "Problem Statement": "",
        "Question": "A heater is being designed that uses a coil of 14-gauge nichrome wire to generate 300 W using a voltage of $$V = 110 \\text{V}$$ . How long should the engineer make the wire?",
        "Image Links": [],
        "Answer": "$$\\left .\\begin{matrix}{} \\\\  \\\\ P = \\frac{V^{2}}{R} \\\\ R = 40 \\text{omega}\\end{matrix}\\right .$$ , $$\\left .\\begin{matrix}{a}A = 2.08 \\text{mm}^{2} \\\\ \\rho = 100 \\times 10^{-8} \\text{omega} \\cdotp \\text{m} \\\\ R = \\rho \\frac{L}{A} \\\\ L = 83 \\text{m}\\end{matrix}\\right .$$",
        "Answer Image Links": []
    },
    {
        "Topic": "9.5 Electrical Energy and Power",
        "Problem Statement": "",
        "Question": "An alternative to CFL bulbs and incandescent bulbs are light-emitting diode (LED) bulbs. A 100-W incandescent bulb can be replaced by a 16-W LED bulb. Both produce 1600 lumens of light. Assuming the cost of electricity is $0.10 per kilowatt-hour, how much does it cost to run the bulb for one year if it runs for four hours a day?",
        "Image Links": [],
        "Answer": "",
        "Answer Image Links": []
    },
    {
        "Topic": "9.5 Electrical Energy and Power",
        "Problem Statement": "",
        "Question": "The power dissipated by a resistor with a resistance of $$R = 100 \\text{omega}$$ is $$P = 2.0 \\text{W}$$ . What are the current through and the voltage drop across the resistor?",
        "Image Links": [],
        "Answer": "$$I = 0.14 \\text{A} , V = 14 \\text{V}$$",
        "Answer Image Links": []
    },
    {
        "Topic": "9.5 Electrical Energy and Power",
        "Problem Statement": "",
        "Question": "Running late to catch a plane, a driver accidentally leaves the headlights on after parking the car in the airport parking lot. During takeoff, the driver realizes the mistake. Having just replaced the battery, the driver knows that the battery is a 12-V automobile battery, rated at 100 $$\\text{A} \\cdotp \\text{h}$$ . The driver, knowing there is nothing that can be done, estimates how long the lights will shine, assuming there are two 12-V headlights, each rated at 40 W. What did the driver conclude?",
        "Image Links": [],
        "Answer": "",
        "Answer Image Links": []
    },
    {
        "Topic": "9.5 Electrical Energy and Power",
        "Problem Statement": "",
        "Question": "A physics student has a single-occupancy dorm room. The student has a small refrigerator that runs with a current of 3.00 A and a voltage of 110 V, a lamp that contains a 100-W bulb, an overhead light with a 60-W bulb, and various other small devices adding up to 3.00 W. (a) Assuming the power plant that supplies 110 V electricity to the dorm is 10 km away and the two aluminum transmission cables use 0-gauge wire with a diameter of 8.252 mm, estimate the percentage of the total power supplied by the power company that is lost in the transmission. (b) What would be the result is the power company delivered the electric power at 110 kV?",
        "Image Links": [],
        "Answer": "a. $$\\left .\\begin{matrix}{} \\\\  \\\\ I \\approx 3.00 \\text{A} + \\frac{100 \\text{W}}{110 \\text{V}} + \\frac{60 \\text{W}}{110 \\text{V}} + \\frac{3.00 \\text{W}}{110 \\text{V}} = 4.48 \\text{A} \\\\ P = 493 \\text{W} \\\\ R = 9.91 \\text{omega} , \\\\ P_{\\text{loss}} = 200. \\text{W} \\\\ \\text{%} \\text{loss} = 40 \\text{%}\\end{matrix}\\right .$$ b. $$\\left .\\begin{matrix}{a}P = 493 \\text{W} \\\\ I = 0.0045 \\text{A} \\\\ R = 9.91 \\text{omega} \\\\ P_{\\text{loss}} = 201 \\mu \\text{W} \\\\ \\text{%} \\text{loss} = 0.00004 \\text{%}\\end{matrix}\\right .$$",
        "Answer Image Links": []
    },
    {
        "Topic": "9.5 Electrical Energy and Power",
        "Problem Statement": "",
        "Question": "A 0.50-W, $$220 \\text{-} \\text{omega}$$ resistor carries the maximum current possible without damaging the resistor. If the current were reduced to half the value, what would be the power consumed?",
        "Image Links": [],
        "Answer": "",
        "Answer Image Links": []
    },
    {
        "Topic": "9.6 Superconductors",
        "Problem Statement": "",
        "Question": "Consider a power plant is located 60 km away from a residential area uses 0-gauge $$( A = 42.40 \\text{mm}^{2} )$$ wire of copper to transmit power at a current of $$I = 100.00 \\text{A}$$ . How much more power is dissipated in the copper wires than it would be in superconducting wires?",
        "Image Links": [],
        "Answer": "$$\\left .\\begin{matrix}{} \\\\  \\\\  \\\\  \\\\ R_{\\text{copper}} = 23.77 \\text{omega} \\\\ P = 2.377 \\times 10^{5} \\text{W}\\end{matrix}\\right .$$",
        "Answer Image Links": []
    },
    {
        "Topic": "9.6 Superconductors",
        "Problem Statement": "",
        "Question": "A wire is drawn through a die, stretching it to four times its original length. By what factor does its resistance increase?",
        "Image Links": [],
        "Answer": "",
        "Answer Image Links": []
    },
    {
        "Topic": "9.6 Superconductors",
        "Problem Statement": "",
        "Question": "Digital medical thermometers determine temperature by measuring the resistance of a semiconductor device called a thermistor (which has $$\\alpha = -0.06 \\text{/} \\text{\u00b0} \\text{C}$$ ) when it is at the same temperature as the patient. What is a patient\u2019s temperature if the thermistor\u2019s resistance at that temperature is 82.0% of its value at $$37 \\text{\u00b0} \\text{C}$$ (normal body temperature)?",
        "Image Links": [],
        "Answer": "$$\\left .\\begin{matrix}{a}R = R_{0} ( 1 + \\alpha ( T - T_{0} ) ) \\\\ 0.82 R_{0} = R_{0} ( 1 + \\alpha ( T - T_{0} ) ) , 0.82 = 1 - 0.06 ( T - 37 \\text{\u00b0} \\text{C} ) , T = 40 \\text{\u00b0} \\text{C}\\end{matrix}\\right .$$",
        "Answer Image Links": []
    },
    {
        "Topic": "9.6 Superconductors",
        "Problem Statement": "",
        "Question": "Electrical power generators are sometimes \u201cload tested\u201d by passing current through a large vat of water. A similar method can be used to test the heat output of a resistor. A $$R = 30 \\text{omega}$$ resistor is connected to a 9.0-V battery and the resistor leads are waterproofed and the resistor is placed in 1.0 kg of room temperature water $$( T = 20 \\text{\u00b0} \\text{C} )$$ . Current runs through the resistor for 20 minutes. Assuming all the electrical energy dissipated by the resistor is converted to heat, what is the final temperature of the water?",
        "Image Links": [],
        "Answer": "",
        "Answer Image Links": []
    },
    {
        "Topic": "9.6 Superconductors",
        "Problem Statement": "",
        "Question": "A 12-gauge gold wire has a length of 1 meter. (a) What would be the length of a silver 12-gauge wire with the same resistance? (b) What are their respective resistances at the temperature of boiling water?",
        "Image Links": [],
        "Answer": "a. $$R_{\\text{Au}} = R_{\\text{Ag}} , \\rho_{\\text{Au}} \\frac{L_{\\text{Au}}}{A_{\\text{Au}}} = \\rho_{\\text{Ag}} \\frac{L_{\\text{Ag}}}{A_{\\text{Ag}}} , L_{\\text{Ag}} = 1.53 \\text{m}$$ ; b. $$R_{\\text{Au,20 \u00b0C}} = 0.0074 \\text{omega} , R_{\\text{Au,100 \u00b0C}} = 0.0094 \\text{omega} , R_{\\text{Ag} , 100 \\text{\u00b0C}} = 0.0096 \\text{omega}$$",
        "Answer Image Links": []
    },
    {
        "Topic": "9.6 Superconductors",
        "Problem Statement": "",
        "Question": "What is the change in temperature required to decrease the resistance for a carbon resistor by 10%?",
        "Image Links": [],
        "Answer": "",
        "Answer Image Links": []
    }
]