[
    {
        "Topic": "",
        "Problem Statement": "For the following exercises, find $$f^{\\prime} ( x )$$ for each function.",
        "Question": "$$f ( x ) = x^{2} e^{x}$$",
        "Image Links": [],
        "Answer": "$$2 x e^{x} + x^{2} e^{x}$$",
        "Answer Image Links": []
    },
    {
        "Topic": "",
        "Problem Statement": "For the following exercises, find $$f^{\\prime} ( x )$$ for each function.",
        "Question": "$$f ( x ) = \\frac{e^{\\text{unicode[:-]} x}}{x}$$",
        "Image Links": [],
        "Answer": "",
        "Answer Image Links": []
    },
    {
        "Topic": "",
        "Problem Statement": "For the following exercises, find $$f^{\\prime} ( x )$$ for each function.",
        "Question": "$$f ( x ) = e^{x^{3} \\text{ln} x}$$",
        "Image Links": [],
        "Answer": "$$e^{x^{3} \\text{ln} x} ( 3 x^{2} \\text{ln} x + x^{2} )$$",
        "Answer Image Links": []
    },
    {
        "Topic": "",
        "Problem Statement": "For the following exercises, find $$f^{\\prime} ( x )$$ for each function.",
        "Question": "$$f ( x ) = \\sqrt{e^{2 x} + 2 x}$$",
        "Image Links": [],
        "Answer": "",
        "Answer Image Links": []
    },
    {
        "Topic": "",
        "Problem Statement": "For the following exercises, find $$f^{\\prime} ( x )$$ for each function.",
        "Question": "$$f ( x ) = \\frac{e^{x} - e^{\\text{unicode[:-]} x}}{e^{x} + e^{\\text{unicode[:-]} x}}$$",
        "Image Links": [],
        "Answer": "$$\\frac{4}{( e^{x} + e^{\\text{unicode[:-]} x} )^{2}}$$",
        "Answer Image Links": []
    },
    {
        "Topic": "",
        "Problem Statement": "For the following exercises, find $$f^{\\prime} ( x )$$ for each function.",
        "Question": "$$f ( x ) = \\frac{10^{x}}{\\text{ln} 10}$$",
        "Image Links": [],
        "Answer": "",
        "Answer Image Links": []
    },
    {
        "Topic": "",
        "Problem Statement": "For the following exercises, find $$f^{\\prime} ( x )$$ for each function.",
        "Question": "$$f ( x ) = 2^{4 x} + 4 x^{2}$$",
        "Image Links": [],
        "Answer": "$$2^{4 x + 2} \\cdotp \\text{ln} 2 + 8 x$$",
        "Answer Image Links": []
    },
    {
        "Topic": "",
        "Problem Statement": "For the following exercises, find $$f^{\\prime} ( x )$$ for each function.",
        "Question": "$$f ( x ) = 3^{\\text{sin} 3 \\text{x}}$$",
        "Image Links": [],
        "Answer": "",
        "Answer Image Links": []
    },
    {
        "Topic": "",
        "Problem Statement": "For the following exercises, find $$f^{\\prime} ( x )$$ for each function.",
        "Question": "$$f ( x ) = x^{\\pi} \\cdotp \\pi^{x}$$",
        "Image Links": [],
        "Answer": "$$\\pi x^{\\pi - 1} \\cdotp \\pi^{x} + x^{\\pi} \\cdotp \\pi^{x} \\text{ln} \\pi$$",
        "Answer Image Links": []
    },
    {
        "Topic": "",
        "Problem Statement": "For the following exercises, find $$f^{\\prime} ( x )$$ for each function.",
        "Question": "$$f ( x ) = \\text{ln} ( 4 x^{3} + x )$$",
        "Image Links": [],
        "Answer": "",
        "Answer Image Links": []
    },
    {
        "Topic": "",
        "Problem Statement": "For the following exercises, find $$f^{\\prime} ( x )$$ for each function.",
        "Question": "$$f ( x ) = \\text{ln} \\sqrt{5 x - 7}$$",
        "Image Links": [],
        "Answer": "$$\\frac{5}{2 ( 5 x - 7 )}$$",
        "Answer Image Links": []
    },
    {
        "Topic": "",
        "Problem Statement": "For the following exercises, find $$f^{\\prime} ( x )$$ for each function.",
        "Question": "$$f ( x ) = x^{2} \\text{ln} 9 x$$",
        "Image Links": [],
        "Answer": "",
        "Answer Image Links": []
    },
    {
        "Topic": "",
        "Problem Statement": "For the following exercises, find $$f^{\\prime} ( x )$$ for each function.",
        "Question": "$$f ( x ) = \\text{log} ( \\text{sec} x )$$",
        "Image Links": [],
        "Answer": "$$\\frac{\\text{tan} x}{\\text{ln} 10}$$",
        "Answer Image Links": []
    },
    {
        "Topic": "",
        "Problem Statement": "For the following exercises, find $$f^{\\prime} ( x )$$ for each function.",
        "Question": "$$f ( x ) = \\text{log}_{7} ( 6 x^{4} + 3 )^{5}$$",
        "Image Links": [],
        "Answer": "",
        "Answer Image Links": []
    },
    {
        "Topic": "",
        "Problem Statement": "For the following exercises, find $$f^{\\prime} ( x )$$ for each function.",
        "Question": "$$f ( x ) = 2^{x} \\cdotp \\text{log}_{3} 7^{x^{2} - 4}$$",
        "Image Links": [],
        "Answer": "$$2^{x} \\cdotp \\text{ln} 2 \\cdotp \\text{log}_{3} 7^{x^{2} - 4} + 2^{x} \\cdotp \\frac{2 x \\text{ln} 7}{\\text{ln} 3}$$",
        "Answer Image Links": []
    },
    {
        "Topic": "",
        "Problem Statement": "For the following exercises, use logarithmic differentiation to find $$\\frac{d y}{d x} .$$",
        "Question": "$$y = x^{\\sqrt{x}}$$",
        "Image Links": [],
        "Answer": "",
        "Answer Image Links": []
    },
    {
        "Topic": "",
        "Problem Statement": "For the following exercises, use logarithmic differentiation to find $$\\frac{d y}{d x} .$$",
        "Question": "$$y = ( \\text{sin} 2 x )^{4 x}$$",
        "Image Links": [],
        "Answer": "$$( \\text{sin} 2 x )^{4 x} [ 4 \\cdotp \\text{ln} ( \\text{sin} 2 x ) + 8 x \\cdotp \\text{cot} 2 x ]$$",
        "Answer Image Links": []
    },
    {
        "Topic": "",
        "Problem Statement": "For the following exercises, use logarithmic differentiation to find $$\\frac{d y}{d x} .$$",
        "Question": "$$y = ( \\text{ln} x )^{\\text{ln} x}$$",
        "Image Links": [],
        "Answer": "",
        "Answer Image Links": []
    },
    {
        "Topic": "",
        "Problem Statement": "For the following exercises, use logarithmic differentiation to find $$\\frac{d y}{d x} .$$",
        "Question": "$$y = x^{\\text{log}_{2} x}$$",
        "Image Links": [],
        "Answer": "$$x^{\\text{log}_{2} x} \\cdotp \\frac{2 \\text{ln} x}{x \\text{ln} 2}$$",
        "Answer Image Links": []
    },
    {
        "Topic": "",
        "Problem Statement": "For the following exercises, use logarithmic differentiation to find $$\\frac{d y}{d x} .$$",
        "Question": "$$y = ( x^{2} - 1 )^{\\text{ln} x}$$",
        "Image Links": [],
        "Answer": "",
        "Answer Image Links": []
    },
    {
        "Topic": "",
        "Problem Statement": "For the following exercises, use logarithmic differentiation to find $$\\frac{d y}{d x} .$$",
        "Question": "$$y = x^{\\text{cot} x}$$",
        "Image Links": [],
        "Answer": "$$x^{\\text{cot} x} \\cdotp [ \\text{unicode[:-]} \\text{csc}^{2} x \\cdotp \\text{ln} x + \\frac{\\text{cot} x}{x} ]$$",
        "Answer Image Links": []
    },
    {
        "Topic": "",
        "Problem Statement": "For the following exercises, use logarithmic differentiation to find $$\\frac{d y}{d x} .$$",
        "Question": "$$y = \\frac{x + 11}{\\sqrt[3]{x^{2} - 4}}$$",
        "Image Links": [],
        "Answer": "",
        "Answer Image Links": []
    },
    {
        "Topic": "",
        "Problem Statement": "For the following exercises, use logarithmic differentiation to find $$\\frac{d y}{d x} .$$",
        "Question": "$$y = x^{-1 \\text{/} 2} ( x^{2} + 3 )^{2 \\text{/} 3} ( 3 x - 4 )^{4}$$",
        "Image Links": [],
        "Answer": "$$x^{-1 \\text{/} 2} ( x^{2} + 3 )^{2 \\text{/} 3} ( 3 x - 4 )^{4} \\cdotp [ \\frac{-1}{2 x} + \\frac{4 x}{3 ( x^{2} + 3 )} + \\frac{12}{3 x - 4} ]$$",
        "Answer Image Links": []
    },
    {
        "Topic": "",
        "Problem Statement": "For the following exercises, use logarithmic differentiation to find $$\\frac{d y}{d x} .$$",
        "Question": "[T] Find an equation of the tangent line to the graph of $$f ( x ) = 4 x e^{( x^{2} - 1 )}$$ at the point where $$x = -1 .$$ Graph both the function and the tangent line.",
        "Image Links": [],
        "Answer": "",
        "Answer Image Links": []
    },
    {
        "Topic": "",
        "Problem Statement": "For the following exercises, use logarithmic differentiation to find $$\\frac{d y}{d x} .$$",
        "Question": "[T] Find the equation of the line that is normal to the graph of $$f ( x ) = x \\cdotp 5^{x}$$ at the point where $$x = 1 .$$ Graph both the function and the normal line.",
        "Image Links": [],
        "Answer": "$$y = \\frac{-1}{5 + 5 \\text{ln} 5} x + ( 5 + \\frac{1}{5 + 5 \\text{ln} 5} )$$",
        "Answer Image Links": [
            "https://openstax.org/apps/archive/20240812.170248/resources/60a8689b1c73b7bbbde9f21f0af698cda983d206"
        ]
    },
    {
        "Topic": "",
        "Problem Statement": "For the following exercises, use logarithmic differentiation to find $$\\frac{d y}{d x} .$$",
        "Question": "[T] Find the equation of the tangent line to the graph of $$x^{3} - x \\text{ln} y + y^{3} = 2 x + 5$$ at the point (2, 1). ( Hint : Use implicit differentiation to find $$\\frac{d y}{d x} . )$$ Graph both the curve and the tangent line.",
        "Image Links": [],
        "Answer": "",
        "Answer Image Links": []
    },
    {
        "Topic": "",
        "Problem Statement": "For the following exercises, use logarithmic differentiation to find $$\\frac{d y}{d x} .$$",
        "Question": "Consider the function $$y = x^{1 \\text{/} x}$$ for $$x > 0 .$$ Determine the points on the graph where the tangent line is horizontal. Determine the points on the graph where $$y^{\\prime} > 0$$ and those where $$y^{\\prime} < 0 .$$",
        "Image Links": [],
        "Answer": "a. $$x = e \\tilde{} 2.718$$ b. $$y \\prime \\  > \\  0 \\  \\text{on} \\  ( 0 , \\  e ) ; \\  y \\prime \\  < \\  0 \\  \\text{on} \\  ( e , \\  \\infty )$$",
        "Answer Image Links": []
    },
    {
        "Topic": "",
        "Problem Statement": "For the following exercises, use logarithmic differentiation to find $$\\frac{d y}{d x} .$$",
        "Question": "The formula $$I ( t ) = \\frac{\\text{sin} t}{e^{t}}$$ is the formula for a decaying alternating current. Complete the following table with the appropriate values. \\begin{table}[h]\n\\centering\n\\begin{tabular}{|c|c|}\n\\hline\n$$t$$ & $$\\frac{\\text{sin} t}{e^{t}}$$ \\\\ \\hline\n0 & (i) \\\\ \\hline\n$$\\frac{\\pi}{2}$$ & (ii) \\\\ \\hline\n$$\\pi$$ & (iii) \\\\ \\hline\n$$\\frac{3 \\pi}{2}$$ & (iv) \\\\ \\hline\n$$2 \\pi$$ & (v) \\\\ \\hline\n$$\\frac{5 \\pi}{2}$$ & (vi) \\\\ \\hline\n$$3 \\pi$$ & (vii) \\\\ \\hline\n$$\\frac{7 \\pi}{2}$$ & (viii) \\\\ \\hline\n$$4 \\pi$$ & (ix) \\\\ \\hline\n\\end{tabular}\n\\end{table} Using only the values in the table, determine where the tangent line to the graph of $$I ( t )$$ is horizontal.",
        "Image Links": [],
        "Answer": "",
        "Answer Image Links": []
    },
    {
        "Topic": "",
        "Problem Statement": "For the following exercises, use logarithmic differentiation to find $$\\frac{d y}{d x} .$$",
        "Question": "[T] The population of Toledo, Ohio, in 2000 was approximately 500,000. Assume the population is increasing at a rate of 5% per year. Write the exponential function that relates the total population as a function of $$t .$$ Use a. to determine the rate at which the population is increasing in $$t$$ years. Use b. to determine the rate at which the population is increasing in 10 years.",
        "Image Links": [],
        "Answer": "a. $$P = 500,000 ( 1.05 )^{t}$$ individuals b. $$P^{\\prime} ( t ) = 24395 \\cdotp ( 1.05 )^{t}$$ individuals per year c. $$39,737$$ individuals per year",
        "Answer Image Links": []
    },
    {
        "Topic": "",
        "Problem Statement": "For the following exercises, use logarithmic differentiation to find $$\\frac{d y}{d x} .$$",
        "Question": "[T] An isotope of the element erbium has a half-life of approximately 12 hours. Initially there are 9 grams of the isotope present. Write the exponential function that relates the amount of substance remaining as a function of $$t ,$$ measured in hours. Use a. to determine the rate at which the substance is decaying in $$t$$ hours. Use b. to determine the rate of decay at $$t = 4$$ hours.",
        "Image Links": [],
        "Answer": "",
        "Answer Image Links": []
    },
    {
        "Topic": "",
        "Problem Statement": "For the following exercises, use logarithmic differentiation to find $$\\frac{d y}{d x} .$$",
        "Question": "[T] The number of cases of influenza in New York City from the beginning of 1960 to the beginning of 1964 is modeled by the function $$N ( t ) = 5.3 e^{0.093 t^{2} - 0.87 t} , ( 0 \\le t \\le 4 ) ,$$ where $$N ( t )$$ gives the number of cases (in thousands) and t is measured in years, with $$t = 0$$ corresponding to the beginning of 1960. Show work that evaluates $$N ( 0 )$$ and $$N ( 4 ) .$$ Briefly describe what these values indicate about the disease in New York City. Show work that evaluates $$N^{\\prime} ( 0 )$$ and $$N^{\\prime} ( 3 ) .$$ Briefly describe what these values indicate about the disease in New York City.",
        "Image Links": [],
        "Answer": "a. At the beginning of 1960 there were 5.3 thousand cases of the disease in New York City. At the beginning of 1964 there were approximately 723 cases of the disease in the United States. b. At the beginning of 1960 the number of cases of the disease was decreasing at rate of $$-4.611$$ thousand per year; at the beginning of 1963, the number of cases of the disease was decreasing at a rate of $$-0.2808$$ thousand per year.",
        "Answer Image Links": []
    },
    {
        "Topic": "",
        "Problem Statement": "For the following exercises, use logarithmic differentiation to find $$\\frac{d y}{d x} .$$",
        "Question": "[T] The relative rate of change of a differentiable function $$y = f ( x )$$ is given by $$\\frac{100 \\cdotp f^{\\prime} ( x )}{f ( x )} \\text{%} .$$ One model for population growth is a Gompertz growth function, given by $$P ( x ) = a e^{\\text{unicode[:-]} b \\cdotp e^{\\text{unicode[:-]} c x}}$$ where $$a , b ,$$ and $$c$$ are constants. Find the relative rate of change formula for the generic Gompertz function. Use a. to find the relative rate of change of a population in $$x = 20$$ months when $$a = 204 , b = 0.0198 ,$$ and $$c = 0.15 .$$ Briefly interpret what the result of b. means.",
        "Image Links": [],
        "Answer": "",
        "Answer Image Links": []
    },
    {
        "Topic": "",
        "Problem Statement": "For the following exercises, use the population of New York City from 1790 to 1860, given in the following table. \\begin{table}[h]\n\\centering\n\\begin{tabular}{|c|c|}\n\\hline\nYears since 1790 & Population \\\\ \\hline\n0 & 33,131 \\\\ \\hline\n10 & 60,515 \\\\ \\hline\n20 & 96,373 \\\\ \\hline\n30 & 123,706 \\\\ \\hline\n40 & 202,300 \\\\ \\hline\n50 & 312,710 \\\\ \\hline\n60 & 515,547 \\\\ \\hline\n70 & 813,669 \\\\ \\hline\n\\end{tabular}\n\\end{table} Table 3.8 New York City Population Over Time Source: http://en.wikipedia.org/wiki/Largest_cities_in_the_United_States _by_population_by_decade.",
        "Question": "[T] Using a computer program or a calculator, fit a growth curve to the data of the form $$p = a b^{t} .$$",
        "Image Links": [],
        "Answer": "$$p = 35741 ( 1.045 )^{t}$$",
        "Answer Image Links": []
    },
    {
        "Topic": "",
        "Problem Statement": "For the following exercises, use the population of New York City from 1790 to 1860, given in the following table. \\begin{table}[h]\n\\centering\n\\begin{tabular}{|c|c|}\n\\hline\nYears since 1790 & Population \\\\ \\hline\n0 & 33,131 \\\\ \\hline\n10 & 60,515 \\\\ \\hline\n20 & 96,373 \\\\ \\hline\n30 & 123,706 \\\\ \\hline\n40 & 202,300 \\\\ \\hline\n50 & 312,710 \\\\ \\hline\n60 & 515,547 \\\\ \\hline\n70 & 813,669 \\\\ \\hline\n\\end{tabular}\n\\end{table} Table 3.8 New York City Population Over Time Source: http://en.wikipedia.org/wiki/Largest_cities_in_the_United_States _by_population_by_decade.",
        "Question": "[T] Using the exponential best fit for the data, write a table containing the derivatives evaluated at each year.",
        "Image Links": [],
        "Answer": "",
        "Answer Image Links": []
    },
    {
        "Topic": "",
        "Problem Statement": "For the following exercises, use the population of New York City from 1790 to 1860, given in the following table. \\begin{table}[h]\n\\centering\n\\begin{tabular}{|c|c|}\n\\hline\nYears since 1790 & Population \\\\ \\hline\n0 & 33,131 \\\\ \\hline\n10 & 60,515 \\\\ \\hline\n20 & 96,373 \\\\ \\hline\n30 & 123,706 \\\\ \\hline\n40 & 202,300 \\\\ \\hline\n50 & 312,710 \\\\ \\hline\n60 & 515,547 \\\\ \\hline\n70 & 813,669 \\\\ \\hline\n\\end{tabular}\n\\end{table} Table 3.8 New York City Population Over Time Source: http://en.wikipedia.org/wiki/Largest_cities_in_the_United_States _by_population_by_decade.",
        "Question": "[T] Using the exponential best fit for the data, write a table containing the second derivatives evaluated at each year.",
        "Image Links": [],
        "Answer": "\\begin{table}[h]\n\\centering\n\\begin{tabular}{|c|c|}\n\\hline\nYears since 1790 & $$P^{\\second}$$ \\\\ \\hline\n0 & 69.25 \\\\ \\hline\n10 & 107.5 \\\\ \\hline\n20 & 167.0 \\\\ \\hline\n30 & 259.4 \\\\ \\hline\n40 & 402.8 \\\\ \\hline\n50 & 625.5 \\\\ \\hline\n60 & 971.4 \\\\ \\hline\n70 & 1508.5 \\\\ \\hline\n\\end{tabular}\n\\end{table}",
        "Answer Image Links": []
    },
    {
        "Topic": "",
        "Problem Statement": "For the following exercises, use the population of New York City from 1790 to 1860, given in the following table. \\begin{table}[h]\n\\centering\n\\begin{tabular}{|c|c|}\n\\hline\nYears since 1790 & Population \\\\ \\hline\n0 & 33,131 \\\\ \\hline\n10 & 60,515 \\\\ \\hline\n20 & 96,373 \\\\ \\hline\n30 & 123,706 \\\\ \\hline\n40 & 202,300 \\\\ \\hline\n50 & 312,710 \\\\ \\hline\n60 & 515,547 \\\\ \\hline\n70 & 813,669 \\\\ \\hline\n\\end{tabular}\n\\end{table} Table 3.8 New York City Population Over Time Source: http://en.wikipedia.org/wiki/Largest_cities_in_the_United_States _by_population_by_decade.",
        "Question": "[T] Using the tables of first and second derivatives and the best fit, answer the following questions: Will the model be accurate in predicting the future population of New York City? Why or why not? Estimate the population in 2010. Was the prediction correct from a.?",
        "Image Links": [],
        "Answer": "",
        "Answer Image Links": []
    }
]